chime.py
themes/big-sur/error.wav
themes/big-sur/info.wav
themes/big-sur/success.wav
themes/big-sur/warning.wav
themes/chime/error.wav
themes/chime/info.wav
themes/chime/success.wav
themes/chime/warning.wav
themes/mario/error.wav
themes/mario/info.wav
themes/mario/success.wav
themes/mario/warning.wav
themes/material/error.wav
themes/material/info.wav
themes/material/success.wav
themes/material/warning.wav
themes/sonic/error.wav
themes/sonic/info.wav
themes/sonic/success.wav
themes/sonic/warning.wav
themes/zelda/error.wav
themes/zelda/info.wav
themes/zelda/success.wav
themes/zelda/warning.wav
chime-0.5.3.dist-info/entry_points.txt
chime-0.5.3.dist-info/LICENSE
chime-0.5.3.dist-info/WHEEL
chime-0.5.3.dist-info/METADATA
chime-0.5.3.dist-info/RECORD
