Metadata-Version: 2.1
Name: chime
Version: 0.5.3
Summary: Python sound notifications made easy.
Home-page: https://github.com/MaxHalford/chime
License: MIT
Keywords: notifications,sound,wav
Author: Max Halford
Author-email: maxhalford25@gmail.com
Requires-Python: >=3.6,<4.0
Classifier: License :: OSI Approved :: MIT License
Classifier: Programming Language :: Python :: 3
Classifier: Programming Language :: Python :: 3.10
Classifier: Programming Language :: Python :: 3.6
Classifier: Programming Language :: Python :: 3.7
Classifier: Programming Language :: Python :: 3.8
Classifier: Programming Language :: Python :: 3.9
Project-URL: Repository, https://github.com/MaxHalford/chime
